paquete/__init__.py
paquete/saludos.py
paquete/setup.py
paquete/adios/__init__.py
paquete/adios/despedidas.py
paquete/hola/__init__.py
paquete/hola/saludos.py
tests/__init__.py
tests/test_hola.py
Mensajes_Hectorav06-6.0.dist-info/LICENSE
Mensajes_Hectorav06-6.0.dist-info/METADATA
Mensajes_Hectorav06-6.0.dist-info/WHEEL
Mensajes_Hectorav06-6.0.dist-info/top_level.txt
Mensajes_Hectorav06-6.0.dist-info/RECORD
