Metadata-Version: 2.1
Name: Mensajes-Hectorav06
Version: 6.0
Summary: Un paquete para saludar y despedir
Home-page: http://hectorav.info
Author: Hector Alvarez Vazquez
Author-email: hola@hector.dev
Classifier: Environment :: Console
Classifier: Intended Audience :: Developers
Classifier: License :: OSI Approved :: MIT License
Classifier: Operating System :: OS Independent
Classifier: Programming Language :: Python
Classifier: Programming Language :: Python :: 3.8
Classifier: Programming Language :: Python :: 3.9
Classifier: Topic :: Utilities
License-File: LICENSE
